robot_resources/__init__.py
robot_resources-0.0.1.dist-info/METADATA
robot_resources-0.0.1.dist-info/WHEEL
robot_resources-0.0.1.dist-info/top_level.txt
robot_resources-0.0.1.dist-info/RECORD
