Metadata-Version: 2.4
Name: robot-resources
Version: 0.0.1
Summary: AI agent runtime infrastructure - placeholder package
Author-email: Robot Resources Team <manuelsobrino6@gmail.com>
Project-URL: Homepage, https://github.com/robot-resources
Classifier: Development Status :: 1 - Planning
Classifier: Intended Audience :: Developers
Classifier: License :: OSI Approved :: MIT License
Classifier: Programming Language :: Python :: 3
Classifier: Programming Language :: Python :: 3.8
Classifier: Programming Language :: Python :: 3.9
Classifier: Programming Language :: Python :: 3.10
Classifier: Programming Language :: Python :: 3.11
Classifier: Programming Language :: Python :: 3.12
Requires-Python: >=3.8
